CHANGES.rst
CONTRIBUTORS.rst
MANIFEST.in
README.rst
bootstrap-buildout.py
buildout.cfg
setup.py
travis.cfg
docs/LICENSE.GPL
docs/LICENSE.rst
src/collective/__init__.py
src/collective/__init__.pyc
src/collective.portlet.localevents.egg-info/PKG-INFO
src/collective.portlet.localevents.egg-info/SOURCES.txt
src/collective.portlet.localevents.egg-info/dependency_links.txt
src/collective.portlet.localevents.egg-info/entry_points.txt
src/collective.portlet.localevents.egg-info/namespace_packages.txt
src/collective.portlet.localevents.egg-info/not-zip-safe
src/collective.portlet.localevents.egg-info/requires.txt
src/collective.portlet.localevents.egg-info/top_level.txt
src/collective/portlet/__init__.py
src/collective/portlet/__init__.pyc
src/collective/portlet/localevents/__init__.py
src/collective/portlet/localevents/__init__.pyc
src/collective/portlet/localevents/configure.zcml
src/collective/portlet/localevents/events.pt
src/collective/portlet/localevents/events.py
src/collective/portlet/localevents/events.pyc
src/collective/portlet/localevents/interfaces.py
src/collective/portlet/localevents/interfaces.pyc
src/collective/portlet/localevents/setuphandlers.py
src/collective/portlet/localevents/setuphandlers.pyc
src/collective/portlet/localevents/testing.py
src/collective/portlet/localevents/locales/collective.portlet.localevents.pot
src/collective/portlet/localevents/locales/plone-manual.pot
src/collective/portlet/localevents/locales/plone.pot
src/collective/portlet/localevents/locales/update.sh
src/collective/portlet/localevents/locales/de/LC_MESSAGES/collective.portlet.localevents.mo
src/collective/portlet/localevents/locales/de/LC_MESSAGES/collective.portlet.localevents.po
src/collective/portlet/localevents/locales/de/LC_MESSAGES/plone.mo
src/collective/portlet/localevents/locales/de/LC_MESSAGES/plone.po
src/collective/portlet/localevents/profiles/default/browserlayer.xml
src/collective/portlet/localevents/profiles/default/collectiveportletlocalevents_marker.txt
src/collective/portlet/localevents/profiles/default/metadata.xml
src/collective/portlet/localevents/profiles/default/portlets.xml
src/collective/portlet/localevents/tests/__init__.py
src/collective/portlet/localevents/tests/__init__.pyc
src/collective/portlet/localevents/tests/test_robot.py
src/collective/portlet/localevents/tests/test_setup.py
src/collective/portlet/localevents/tests/robot/test_example.robot