Metadata-Version: 1.1
Name: collective.portlet.localevents
Version: 0.1
Summary: an events portlet for plone that only displays events located in the current folder
Home-page: http://pypi.python.org/pypi/collective.portlet.localevents
Author: Harald Friessnegger
Author-email: harald@webmeisterei.com
License: GPL
Keywords: Python Plone
Platform: UNKNOWN
Classifier: Environment :: Web Environment
Classifier: Framework :: Plone
Classifier: Framework :: Plone :: 4.3
Classifier: Programming Language :: Python
Classifier: Programming Language :: Python :: 2.7
